hzkerberos/__init__.py
hzkerberos/c.py
hzkerberos/errors.py
hzkerberos/token_provider.py
hazelcast_kerberos-1.0.0.dist-info/LICENSE.txt
hazelcast_kerberos-1.0.0.dist-info/METADATA
hazelcast_kerberos-1.0.0.dist-info/WHEEL
hazelcast_kerberos-1.0.0.dist-info/top_level.txt
hazelcast_kerberos-1.0.0.dist-info/RECORD
