Metadata-Version: 2.1
Name: hazelcast-kerberos
Version: 1.0.0
Summary: Kerberos Authentication Support for Hazelcast Python Client
Home-page: https://github.com/hazelcast/hazelcast-python-client-kerberos
Author: Hazelcast Inc. Developers
Author-email: info@hazelcast.com
License: Apache 2.0
Keywords: hazelcast,hazelcast client,in-memory data grid,distributed computing,kerberos,authentication
Platform: UNKNOWN
Classifier: Development Status :: 5 - Production/Stable
Classifier: Intended Audience :: Developers
Classifier: License :: OSI Approved :: Apache Software License
Classifier: Natural Language :: English
Classifier: Operating System :: POSIX :: Linux
Classifier: Programming Language :: Python
Classifier: Programming Language :: Python :: 3.5
Classifier: Programming Language :: Python :: 3.6
Classifier: Programming Language :: Python :: 3.7
Classifier: Programming Language :: Python :: 3.8
Classifier: Programming Language :: Python :: 3.9
Classifier: Programming Language :: Python :: Implementation :: CPython
Classifier: Topic :: Software Development :: Libraries :: Python Modules
Requires-Dist: gssapi
